Cpp11Faq/README.md
Cpp11Faq/__init__.py
Cpp11Faq/__main__.py
Cpp11Faq/file.epub
Cpp11Faq/index.html
Cpp11Faq/css/__init__.py
Cpp11Faq/css/annotations.css
Cpp11Faq/css/main.css
Cpp11Faq/css/normalize.css
Cpp11Faq/css/popup.css
Cpp11Faq/font/__init__.py
Cpp11Faq/font/fontello.eot
Cpp11Faq/font/fontello.svg
Cpp11Faq/font/fontello.ttf
Cpp11Faq/font/fontello.woff
Cpp11Faq/img/__init__.py
Cpp11Faq/img/annotator-glyph-sprite.png
Cpp11Faq/img/annotator-icon-sprite.png
Cpp11Faq/img/apple-touch-icon.png
Cpp11Faq/img/cancelfullscreen.png
Cpp11Faq/img/close.png
Cpp11Faq/img/fullscreen.png
Cpp11Faq/img/loader.gif
Cpp11Faq/img/menu-icon.png
Cpp11Faq/img/save.png
Cpp11Faq/img/saved.png
Cpp11Faq/img/settings-s.png
Cpp11Faq/img/settings.png
Cpp11Faq/img/star.png
Cpp11Faq/js/__init__.py
Cpp11Faq/js/epub.js
Cpp11Faq/js/epub.min.js
Cpp11Faq/js/epub.min.map
Cpp11Faq/js/hooks.min.js
Cpp11Faq/js/hooks.min.map
Cpp11Faq/js/reader.js
Cpp11Faq/js/reader.js.map
Cpp11Faq/js/reader.min.js
Cpp11Faq/js/reader.min.map
Cpp11Faq/js/hooks/__init__.py
Cpp11Faq/js/hooks/extensions/__init__.py
Cpp11Faq/js/hooks/extensions/highlight.js
Cpp11Faq/js/libs/__init__.py
Cpp11Faq/js/libs/jquery.min.js
Cpp11Faq/js/libs/localforage.min.js
Cpp11Faq/js/libs/screenfull.js
Cpp11Faq/js/libs/screenfull.min.js
Cpp11Faq/js/libs/zip.min.js
Cpp11Faq/js/plugins/__init__.py
Cpp11Faq/js/plugins/hypothesis.js
Cpp11Faq/js/plugins/search.js
cpp_11_faq-2024.3.1.0.dist-info/METADATA
cpp_11_faq-2024.3.1.0.dist-info/WHEEL
cpp_11_faq-2024.3.1.0.dist-info/entry_points.txt
cpp_11_faq-2024.3.1.0.dist-info/top_level.txt
cpp_11_faq-2024.3.1.0.dist-info/RECORD
